{
  ".": "<point>",
  "-": "<minus>",
  "(": "<open-parentheses>",
  ")": "<close-parentheses>",
  ",": "<comma>",
  ";": "<semicolon>",
  ":": "<colon>",
  "|": "<pipe>",
  "!": "<exclamation>",
  "\"": "<backslash>",
  "#": "<hash>",
  "$": "<dolarsign>",
  "%": "<percentage>",
  "&": "<ampersand>",
  "/": "<slash>",
  "=": "<equal>",
  "?": "<question-mark>",
  "~": "<tilde>",
  "^": "<circumflex>",
  ">": "<greater-than>",
  "<": "<less-than>",
  "ª": "<ordinal>",
  "º": "<number-sign>",
  "—": "<dash>"
}